README.md
setup.py
matlab_python.egg-info/PKG-INFO
matlab_python.egg-info/SOURCES.txt
matlab_python.egg-info/dependency_links.txt
matlab_python.egg-info/not-zip-safe
matlab_python.egg-info/requires.txt
matlab_python.egg-info/top_level.txt
matpy/__init__.py
matpy/_matpy.py
matpy/tools.py