Metadata-Version: 1.1
Name: matlab-python
Version: 0.1.1
Summary: Call matlab from python
Home-page: https://github.com/xbanke/matpy
Author: quantpy
Author-email: quantpy@gmail.com
License: MIT
Keywords: matlab,python,matpy
Platform: UNKNOWN
Classifier: Development Status :: 4 - Beta
Classifier: Environment :: Console
Classifier: Intended Audience :: Developers
Classifier: License :: OSI Approved :: MIT License
Classifier: Operating System :: OS Independent
Classifier: Programming Language :: Python
Classifier: Programming Language :: Python :: Implementation
Classifier: Programming Language :: Python :: 3.6
Classifier: Topic :: Software Development :: Libraries
